dnacauldron/Filter.py
dnacauldron/SequenceRepository.py
dnacauldron/__init__.py
dnacauldron/cli.py
dnacauldron/reports.py
dnacauldron/tools.py
dnacauldron/version.py
dnacauldron/Assembly/Assembly.py
dnacauldron/Assembly/AssemblyFlaw.py
dnacauldron/Assembly/AssemblySimulation.py
dnacauldron/Assembly/__init__.py
dnacauldron/Assembly/AssemblyReportWriter/AssemblyPlotTranslator.py
dnacauldron/Assembly/AssemblyReportWriter/AssemblyReportPlotsMixin.py
dnacauldron/Assembly/AssemblyReportWriter/AssemblyReportWriter.py
dnacauldron/Assembly/AssemblyReportWriter/__init__.py
dnacauldron/Assembly/AssemblyReportWriter/plot_cuts.py
dnacauldron/Assembly/builtin_assembly_classes/BASICAssembly.py
dnacauldron/Assembly/builtin_assembly_classes/BioBrickStandardAssembly.py
dnacauldron/Assembly/builtin_assembly_classes/GibsonAssembly.py
dnacauldron/Assembly/builtin_assembly_classes/LigaseCyclingReactionAssembly.py
dnacauldron/Assembly/builtin_assembly_classes/OligoPairAnnealing.py
dnacauldron/Assembly/builtin_assembly_classes/Type2sRestrictionAssembly.py
dnacauldron/Assembly/builtin_assembly_classes/__init__.py
dnacauldron/AssemblyMix/AssemblyMix.py
dnacauldron/AssemblyMix/AssemblyMixError.py
dnacauldron/AssemblyMix/HomologousAssemblyMix.py
dnacauldron/AssemblyMix/LigaseCyclingReactionMix.py
dnacauldron/AssemblyMix/RestrictionLigationMix.py
dnacauldron/AssemblyMix/__init__.py
dnacauldron/AssemblyMix/StickyEndAssemblyMix/PlotsMixin.py
dnacauldron/AssemblyMix/StickyEndAssemblyMix/SlotsMixin.py
dnacauldron/AssemblyMix/StickyEndAssemblyMix/StickyEndAssemblyMix.py
dnacauldron/AssemblyMix/StickyEndAssemblyMix/__init__.py
dnacauldron/AssemblyMix/mixins/ConnectorsMixin.py
dnacauldron/AssemblyMix/mixins/ConstructsMixin.py
dnacauldron/AssemblyMix/mixins/FragmentsMixin.py
dnacauldron/AssemblyMix/mixins/GraphsMixin.py
dnacauldron/AssemblyMix/mixins/PlotsMixin.py
dnacauldron/AssemblyMix/mixins/__init__.py
dnacauldron/AssemblyPlan/AssemblyPlan.py
dnacauldron/AssemblyPlan/AssemblyPlanSimulation.py
dnacauldron-2.0.12.dist-info/licenses/LICENSE
dnacauldron-2.0.12.dist-info/METADATA
dnacauldron-2.0.12.dist-info/WHEEL
dnacauldron-2.0.12.dist-info/entry_points.txt
dnacauldron-2.0.12.dist-info/top_level.txt
dnacauldron-2.0.12.dist-info/RECORD
