Metadata-Version: 2.4
Name: dnacauldron
Version: 2.0.12
Summary: Cloning simulation for DNA assembly (Golden Gate, Gibson...)
Author: Zulko
License-Expression: MIT
Project-URL: Homepage, https://github.com/Edinburgh-Genome-Foundry/dnacauldron
Keywords: DNA,assembly,cloning,simulator,synthetic biology
License-File: LICENSE
Requires-Dist: Biopython
Requires-Dist: numpy
Requires-Dist: matplotlib
Requires-Dist: fuzzywuzzy
Requires-Dist: pandas
Requires-Dist: scipy
Requires-Dist: networkx
Requires-Dist: dna_features_viewer
Requires-Dist: flametree
Requires-Dist: snapgene_reader
Requires-Dist: proglog
Requires-Dist: xlwt
Requires-Dist: openpyxl
Requires-Dist: python-Levenshtein
Requires-Dist: xlrd
Provides-Extra: reports
Requires-Dist: pdf_reports; extra == "reports"
Dynamic: license-file
